Workbook
Name Attic: 'Cost References'!$C$168:$C$170
Name Microwave: 'Cost References'!$C$202:$C$204
Name WindowsDoors: 'Cost References'!$C$173:$C$174
Name TrueFalse: 'Cost References'!$D$160:$D$161
Name WinterMix: 'Cost References'!$C$69:$C$70
Name RealEstateComm: 'Cost References'!$D$241:$D$244
Name MiniSplit: 'Cost References'!$C$195:$C$199
Name Permits: 'Cost References'!$C$15:$C$17
Name StudWallHeight: 'Cost References'!$D$93:$D$95
Name Electrical: 'Cost References'!$C$144:$C$145
Name Cleaning: 'Cost References'!$D$185:$D$189
Name Insulation: 'Cost References'!$C$165:$C$168
Name FixedPrices: 'Cost References'!$D$225:$D$230
Name ShowerType: 'Cost References'!$C$233:$C$239
Name Cabinets: 'Cost References'!$D$108:$D$121
Name ConcreteWalls: 'Cost References'!$B$74:$B$76
Name Profit: 'Cost References'!$D$207:$D$222
Name CUBICMETERSLAB: LAMBDA(('Take Off'!$D$53*0.09290304*0.1016))
Name CUBICMETERFOUNDATION: LAMBDA(('Take Off'!$C$56/3.28*0.203*'Take Off'!$D$56/3.28))
Name CUBICMETERFOOTING: LAMBDA(('Take Off'!$C$53/3.28*0.5*0.25))
Name DRYWALL_SQFT: LAMBDA(CEILING_SQFT()+WALL_SQFT())
Name WALL_SQFT: LAMBDA('Cost References'!$D$6*('Cost References'!$D$4+1)*8)
Name LINEAR_FOOTAGE: LAMBDA(('Cost References'!$D$2*2)+('Cost References'!$D$3*2))
Name CEILING_SQFT: LAMBDA(('Cost References'!$D$2*'Cost References'!$D$3)*('Cost References'!$D$4+1))

Sheet Take Off
A1: Kestrel Developments - Estimate Form
A2: Client | C2: ----
A3: Date: | C3: =TODAY() -> 46132
A4: Location: | C4: XXX
A5: Agent:
A6: Service | F6: Subtotal | G6: HST | H6: Item total | I6: Running Total
A7: Soft Costs
A8: Overhead | B8: Lot Price
F9: Amount
F10: 135000 | G10: =(F10+D10)*'Cost References'!D11 -> 20250 | H10: =SUM(F10:G10) -> 155250 | I10: =H10 -> 155250 | K10: Material Cost | L10: =H46+H56 -> 11546.342
K11: Labour Costs | L11: =H15+H17+H19+H22+H28+H59+H62+H65+H68+H82+H86+H89+H92+H95+D98+E100+H103+H106+H109+H112+H115+H118+H121+H123+H126+H129+H147+H156+H150+H169 -> 139208.2
K12: Financing per house | L12: =L11+L10 -> 150754.54
K13: Carried by subs | L13: =H89+H82+H103+H56+H46 -> 44206.342
B14: Engineering | K14: Total Financing (with carried items) | L14: =L12-L13 -> 106548.2
F15: 1500 | H15: =SUM(F15:G15) -> 1500 | I15: =H15+I13 -> 1500
B16: Surveys
F17: 850 | H17: =SUM(F17:G17) -> 850 | I17: =H17+I15 -> 2350
B18: Legal
F19: 2500 | H19: =SUM(F19:G19) -> 2500 | I19: =H19+I17 -> 4850
B20: Permits
E21: Choose City
E22: St. John's | F22: =IF(E22='Cost References'!C15,'Cost References'!D15,IF(E22='Cost References'!C16,'Cost References'!D16,IF(E22='Cost References'!C17, 'Cost References'!D17,0))) -> 3000 | H22: =SUM(F22:G22) -> 3000 | I22: =H22+I19 -> 7850
B27: Blueprints
F28: 500 | H28: =SUM(F28:G28) -> 500 | I28: =I26+H28 -> 500
A29: Construction Costs
A30: Lot Prep | B30: Excavation
E31: Included in Lot Price | F31: Amount
G32: =F32*'Cost References'!D11 -> 0 | H32: =F32 | I32: =I28+H32 -> 500
B33: Well
F34: Choose
G35: =F35*'Cost References'!D11 -> 0 | H35: =SUM(F35:G35) -> 0 | I35: =H35+I32 -> 500
B36: Septic
F37: Amount
G38: =F38*'Cost References'!D11 -> 0 | H38: =SUM(F38:G38) -> 0 | I38: =I35+H38 -> 500
B39: Rock Busting
F40: Amount
G41: =F41*'Cost References'!D11 -> 0 | H41: =SUM(F41:G41) -> 0 | I41: =I38+H41 -> 500
B42: Fill
F43: Amount
G44: =F44*'Cost References'!D11 -> 0 | H44: =SUM(F44:G44) -> 0 | I44: =I41+H44 -> 500
B45: Stone | F45: Amount
F46: 1000 | G46: =F46*'Cost References'!D11 -> 150 | H46: =SUM(F46:G46) -> 1150 | I46: =I44+H46 -> 1650
A50: Concrete | B50: Concrete
B51: Material
C52: Footing Lin Ft | D52: Bsmt Floor Sq ft | E52: Winter Mix
C53: 124 | D53: 1200 | E53: No
C55: Wall Lin Ft | D55: Wall Height | E55: Garage | J55: *update the cost reference for winter mix
C56: 124 | D56: 8 | F56: =(CUBICMETERFOOTING()+CUBICMETERFOUNDATION()+CUBICMETERSLAB())*'Cost References'!D67+IF(E53='Cost References'!C69,'Cost References'!D69,IF(E53='Cost References'!C70,'Cost References'!D70)) -> 9040.2971 | G56: =F56*'Cost References'!D11 -> 1356.0446 | H56: =SUM(F56:G56) -> 10396.342 | I56: =I49+H56 -> 10396.342 | J56: * add 4ft wall to wall height options
B57: Footing Labour
D58: Linear Feet
D59: ='Cost References'!D6+5+5+11 -> 143 | F59: =D59*'Cost References'!D83 -> 1001 | G59: =F59*'Cost References'!D11 -> 150.15 | H59: =SUM(F59:G59) -> 1151.15 | I59: =I56+H59 -> 11547.492
B60: Concrete Walls
B61: Labour | D61: Linear Feet | E61: Wall Height
D62: ='Cost References'!D6+5+5+11 -> 143 | E62: 8 | F62: =IF(E62='Cost References'!B74,'Cost References'!D74*D62,IF(E62='Cost References'!B75,'Cost References'!D75*D62,IF(E62='Cost References'!B76,'Cost References'!D76*D62,0))) -> 4504.5 | G62: =F62*'Cost References'!D11 -> 675.675 | H62: =SUM(F62:G62) -> 5180.175 | I62: =I59+H62 -> 16727.667
B63: Concrete Floor
B64: Finish Labour | D64: Square Feet | E64: Misc.
D65: 700 | F65: =D65*'Cost References'!D79+E65 -> 1120 | G65: =F65*'Cost References'!D11 -> 168 | H65: =SUM(F65:G65) -> 1288 | I65: =I62+H65 -> 18015.667
B66: Foundation
B67: Coating | F67: Amount
F68: 500 | G68: =F68*'Cost References'!D11 -> 75 | H68: =SUM(F68:G68) -> 575 | I68: =I65+H68 -> 18590.667
A69: Building Materials | B69: Bennetts HH
B70: Takeoff | F70: Amount
F71: =31834+33004 -> 64838 | G71: =F71*'Cost References'!D11 -> 9725.7 | H71: =SUM(F71:G71) -> 74563.7 | I71: =I68+H71 -> 93154.367
B72: Trusses and floor | E72: Included with BHH | F72: Amount
E73: None | F73: 0 | G73: =F73*'Cost References'!D11 -> 0 | H73: =SUM(F73:G73) -> 0 | I73: =I71+H73 -> 93154.367 | J73: *add option for yes/no here
B74: Windows
B75: & Doors | D75: Enter Amount | E75: Window Type
D76: =8600+1100+(2*145) -> 9990 | E76: None | F76: =IF(E76='Cost References'!C173,D76*'Cost References'!D173,IF(E76='Cost References'!C174,D76*'Cost References'!D174,0)) -> 9990 | G76: =F76*'Cost References'!D11 -> 1498.5 | H76: =SUM(F76:G76) -> 11488.5 | I76: =I73+H76 -> 104642.87
B77: Foundation Insulation
E78: Enter Amount
E79: =('Cost References'!D6*6)/32 -> 22.875 | F79: =E79*'Cost References'!D250 -> 686.25 | G79: =F79*'Cost References'!D11 -> 102.9375 | H79: =SUM(F79:G79) -> 789.1875 | I79: =I76+H79 -> 105432.05
A80: Subtrades (Supply & Install) | B80: Plumbing
D81: # of Bathrooms | E81: Misc.
D82: 4 | E82: 0 | F82: 8900 | G82: =F82*'Cost References'!D11 -> 1335 | H82: =SUM(F82:G82) -> 10235 | I82: =H82+I79 -> 115667.05
B83: Siding & Labour
D85: Boxes of siding
F86: =D86*2*'Cost References'!D253 -> 0 | G86: =F86*'Cost References'!D11 -> 0 | H86: =SUM(F86:G86) -> 0 | I86: =H86+I82 -> 115667.05
B87: Electrical
C88: Sq. Footage | D88: Bsmt Sq Ft | E88: Dwelling Type
C89: 1200 | D89: 0 | E89: Two-Apartment | F89: =IF(E89='Cost References'!C144,'Cost References'!D144,IF(E89='Cost References'!C145,'Cost References'!D145,0)) -> 13500 | G89: =F89*'Cost References'!D11 -> 2025 | H89: =SUM(F89:G89) -> 15525 | I89: =I86+H89 -> 131192.05
B90: Paint &
B91: Plastering | D91: Sq. Footage | E91: Misc.
D92: =DRYWALL_SQFT() -> 5628 | F92: =D92*'Cost References'!D149 -> 11256 | G92: =F92*'Cost References'!D11 -> 1688.4 | H92: =SUM(F92:G92) -> 12944.4 | I92: =I89+H92 -> 144136.45
B93: Cabinets
E94: Allowance
E95: 18000 | F95: =E95 -> 18000 | G95: =F95*'Cost References'!D11 -> 2700 | H95: =SUM(F95:G95) -> 20700 | I95: =I92+H95 -> 164836.45
B96: Flooring
C97: Floor Allow. | D97: Floor Labour | E97: Underlay # Sheets
C98: 8000 | D98: 3900 | E98: =('Cost References'!D2*'Cost References'!D3)/32 -> 28.125
C99: Rails/Spindles | D99: Hardwood Stairs | E99: Labour
D100: 1000 | E100: 1500 | F100: =C98+D98+C100+D100+E100+(E98*'Cost References'!D249) -> 15721.875 | G100: =F100*'Cost References'!D11 -> 2358.2812 | H100: =SUM(F100:G100) -> 18080.156 | I100: =I95+H100 -> 182916.61
B101: HVAC
D102: Secondary Heat | E102: Microwave?
D103: None | E103: None | F103: ='Cost References'!D192+IF(E103='Cost References'!C202,'Cost References'!D202,IF(E103='Cost References'!C203,'Cost References'!D203,IF(E103='Cost References'!C204,'Cost References'!D204,0))) -> 6000 | G103: =F103*'Cost References'!D11 -> 900 | H103: =SUM(F103:G103) -> 6900 | I103: =H103+I100 -> 189816.61 | J103: *Bennetts included 2 range hoods
B104: Tile
D105: Material Price | E105: Sq ft
D106: 5.5 | E106: 100 | F106: =E106*'Cost References'!D246+D106*E106 -> 1100 | G106: =F106*'Cost References'!D11 -> 165 | H106: =SUM(F106:G106) -> 1265 | I106: =H106+I103 -> 191081.61
A107: Labour Only | B107: Front Deck
F108: Amount
F109: 1400 | G109: =F109*'Cost References'!D11 -> 210 | H109: =SUM(F109:G109) -> 1610 | I109: =I106+H109 -> 192691.61
...

Sheet Cost References
A1: House Measurement Multipliers
C2: width(ft) | D2: 25 | E2: Fill in quantities
C3: length(ft) | D3: 36
C4: storeys | D4: 2
C5: VB ceiling sqft | D5: =D2*D3 -> 900
C6: linear footage | D6: =LINEAR_FOOTAGE() -> 122
C7: wall sqft | D7: =WALL_SQFT() -> 2928 | E7: *change this formula to read wall height if different that 8'walls
C8: drywall sqft | D8: =DRYWALL_SQFT() -> 5628
A9: Tax
C11: Rate | D11: 0.15
A13: Permits
B15: $9 per $1000 up to $100,000 & $7.20 per $1000 above $100,000 | C15: St. John's | D15: 3000
C16: Paradise | D16: 3000
C17: Mount Pearl | D17: 2000
A19: Financing Interest Charges
D21: 3500
D22: 4000
D23: 4500
D24: 5000
D25: 5500
D26: 6000
D27: 6500
D28: 7000
D29: 7500
D30: 8000
D31: 8500
D32: 9000
... D34: 10000
A37: Well
C39: Drilling per ft | D39: 27
C40: Casing per ft | D40: 45
C41: Drive shoe | D41: 100
C42: Well cap | D42: 55
C44: Well Depths(ft)
C45: 300 | D45: =(C45*D39)+(C45*D40)+D41+D42 -> 21755
C46: 400 | D46: 12845
C47: 500 | D47: 15545
B49: Based on 50' from dwelling | C49: Pump Systems
C50: 300' | D50: 5200
C51: 500' | D51: 6200
A53: Septic
C55: Traditional | D55: 15000
C56: Class B
A59: Rock Busting
C61: Per hour rate | D61: 275
A64: Concrete
C66: Pump Truck | D66: 185
C67: Per m3 w/ pumper | D67: 260
B68: Winter Mix
C69: Yes | D69: 500
C70: No | D70: 0
B72: Foundation Walls
B73: Wall Height(ft)
B74: 8 | C74: Per linear foot | D74: 31.5
B75: 9 | C75: Per linear foot | D75: 35.5
B76: 10 | C76: Per linear foot | D76: 40.5
B78: Slab
B79: ian whiteway | C79: Finishing per sqft | D79: 1.6
B81: Footings | I81: 185 | J81: per hour
C82: Footing per sqft
C83: labour per sqft | D83: 7
B84: Garage
C85: Rate per sqft | D85: 2
A88: Fill
A91: Framing
B92: Wall Heights
D93: 8
D94: 9
D95: 10
B97: House
C98: labour per sqft | D98: 9
B100: Basement
C101: labour per sqft | D101: 7
B103: Garage
C104: labour per sqft | D104: 7
A106: Cabinets
C108: Fixed Rate | D108: 5000
D109: 6000
D110: 7000
D111: 8000
D112: 9000
D113: 10000
D114: 11000
D115: 12000
D116: 13000
D117: 14000
D118: 15000
D119: 16000
D120: 17000
D121: 18000
C123: Estimate Multiplier per ft
A125: Bathroom
C127: Labour Expense | D127: 2600
C128: Shower Fixtures | D128: =D129+D130+D131+D132 -> 1485
C129: Faucet | D129: 200
C130: Toilet | D130: 235
C131: Vanity(36") | D131: 800
C132: Shower Head | D132: 250
C134: Bathroom Type
C135: All Tile | D135: =1800+900 -> 2700
...
